mcp_code_editor/__init__.py
mcp_code_editor/cli.py
mcp_code_editor/server.py
mcp_code_editor/core/__init__.py
mcp_code_editor/core/models.py
mcp_code_editor/tools/__init__.py
mcp_code_editor/tools/ast_analyzer.py
mcp_code_editor/tools/ast_integration.py
mcp_code_editor/tools/console_tools.py
mcp_code_editor/tools/dependency_analyzer.py
mcp_code_editor/tools/diff_simulator.py
mcp_code_editor/tools/diff_tools.py
mcp_code_editor/tools/file_operations.py
mcp_code_editor/tools/library_indexer.py
mcp_code_editor/tools/project_tools.py
mcp_code_editor-0.1.24.dist-info/licenses/LICENSE
scratch/test.py
mcp_code_editor-0.1.24.dist-info/METADATA
mcp_code_editor-0.1.24.dist-info/WHEEL
mcp_code_editor-0.1.24.dist-info/entry_points.txt
mcp_code_editor-0.1.24.dist-info/top_level.txt
mcp_code_editor-0.1.24.dist-info/RECORD
