Metadata-Version: 2.4
Name: mcp-code-editor
Version: 0.1.24
Summary: A FastMCP server providing powerful code editing tools
Author-email: MCP Code Editor Team <mcpcodeeditor@example.com>
License: MIT
Project-URL: Homepage, https://github.com/alejoair/mcp-code-editor
Project-URL: Bug Reports, https://github.com/alejoair/mcp-code-editor/issues
Project-URL: Source, https://github.com/alejoair/mcp-code-editor
Project-URL: Documentation, https://alejoair.github.io/mcp-code-editor/
Project-URL: Changelog, https://github.com/alejoair/mcp-code-editor/releases
Keywords: mcp,code-editor,fastmcp,development-tools
Classifier: Development Status :: 3 - Alpha
Classifier: Intended Audience :: Developers
Classifier: Topic :: Software Development :: Libraries :: Python Modules
Classifier: Topic :: Text Editors
Classifier: License :: OSI Approved :: MIT License
Classifier: Programming Language :: Python :: 3
Classifier: Programming Language :: Python :: 3.8
Classifier: Programming Language :: Python :: 3.9
Classifier: Programming Language :: Python :: 3.10
Classifier: Programming Language :: Python :: 3.11
Classifier: Programming Language :: Python :: 3.12
Requires-Python: >=3.8
License-File: LICENSE
Requires-Dist: fastmcp>=2.8.0
Provides-Extra: dev
Requires-Dist: build>=0.10.0; extra == "dev"
Requires-Dist: twine>=4.0.0; extra == "dev"
Requires-Dist: pytest>=7.0.0; extra == "dev"
Requires-Dist: pytest-cov>=4.0.0; extra == "dev"
Dynamic: license-file
